git_log_stat/__init__.py
git_log_stat/cli.py
git_log_stat/git_log_stat_service.py
git_log_stat/app_logs/__init__.py
git_log_stat/app_logs/logger_service.py
git_log_stat/git_exporters/__init__.py
git_log_stat/git_exporters/base_exporter.py
git_log_stat/git_exporters/csv_tsv_exporter.py
git_log_stat/git_exporters/docx_exporter.py
git_log_stat/git_exporters/file_exporter.py
git_log_stat/git_exporters/pdf_exporter.py
git_log_stat/git_exporters/ppt_exporter.py
git_log_stat/git_exporters/txt_exporter.py
git_log_stat/git_exporters/xls_exporter.py
git_log_stat/git_repo/__init__.py
git_log_stat/git_repo/git_export_service.py
git_log_stat/git_repo/git_log_format_service.py
git_log_stat/git_repo/git_nlp.py
git_log_stat/git_repo/git_output_service.py
git_log_stat/git_repo/git_repo_service.py
git_log_stat/jira_exporter/__init__.py
git_log_stat/jira_exporter/jira_exporter.py
ibm_git_log_stat-2.0.2.dist-info/licenses/LICENSE
ibm_git_log_stat-2.0.2.dist-info/METADATA
ibm_git_log_stat-2.0.2.dist-info/WHEEL
ibm_git_log_stat-2.0.2.dist-info/entry_points.txt
ibm_git_log_stat-2.0.2.dist-info/top_level.txt
ibm_git_log_stat-2.0.2.dist-info/RECORD
