Metadata-Version: 2.4
Name: ibm-git-log-stat
Version: 2.0.2
Summary: A CLI tool to list git commits and GitHub PRs per user for a date range. Generates output in various file formats with NLP summaries. Fetches JIRA issues as well.
Author-email: Faizan Fordkar <faizan.fordkar@ibm.com>
License: ---
Requires-Python: >=3.12
License-File: LICENSE
Requires-Dist: requests
Requires-Dist: pandas
Requires-Dist: openpyxl
Requires-Dist: transformers
Requires-Dist: torch
Requires-Dist: reportlab
Requires-Dist: python-docx
Requires-Dist: python-pptx
Dynamic: license-file
